how_is_the_weather/__init__.py
how_is_the_weather/weather.py
how_is_the_weather-0.3.2.dist-info/LICENSE
how_is_the_weather-0.3.2.dist-info/METADATA
how_is_the_weather-0.3.2.dist-info/WHEEL
how_is_the_weather-0.3.2.dist-info/RECORD
