Metadata-Version: 2.1
Name: how-is-the-weather
Version: 0.3.2
Summary: A simple tool to describe weather conditions
Home-page: https://github.com/jimbosimbo/howstheweather
License: MIT
Author: Jim Jimbo
Author-email: jim377893@gmail.com
Requires-Python: >=3.8,<4.0
Classifier: License :: OSI Approved :: MIT License
Classifier: Programming Language :: Python :: 3
Classifier: Programming Language :: Python :: 3.8
Classifier: Programming Language :: Python :: 3.9
Classifier: Programming Language :: Python :: 3.10
Classifier: Programming Language :: Python :: 3.11
Classifier: Programming Language :: Python :: 3.12
Requires-Dist: requests (>=2.31.0,<3.0.0)
